std_usage/__init__.py
std_usage/__main__.py
std_usage/std_usage.py
std_usage-1.3.dist-info/METADATA
std_usage-1.3.dist-info/WHEEL
std_usage-1.3.dist-info/top_level.txt
std_usage-1.3.dist-info/RECORD
